Metadata-Version: 2.1
Name: odoo14-addon-base_report_to_label_printer
Version: 14.0.1.0.1.dev7
Summary: Report to label printer
Home-page: https://github.com/OCA/report-print-send
Author: Raumschmiede GmbH - Christopher Hansen, Odoo Community Association (OCA)
Author-email: support@odoo-community.org
License: AGPL-3
Classifier: Programming Language :: Python
Classifier: Framework :: Odoo
Classifier: Framework :: Odoo :: 14.0
Classifier: License :: OSI Approved :: GNU Affero General Public License v3
Requires-Python: >=3.6
Requires-Dist: odoo14-addon-base-report-to-printer
Requires-Dist: odoo<14.1dev,>=14.0a
